{
    "id": "ml_predict_probabilities",
    "summary": "Predict class probabilities using ML",
    "description": "Applies a machine learning model to a data cube of input features and returns the predicted class probabilities.",
    "categories": [
        "machine learning"
    ],
    "experimental": true,
    "parameters": [
        {
            "name": "data",
            "description": "The data cube containing the input features.",
            "schema": {
                "type": "object",
                "subtype": "datacube"
            }
        },
        {
            "name": "model",
            "description": "A ML model that was trained and supports probability predictions.",
            "schema": {
                "type": "object",
                "subtype": "ml-model"
            }
        },
        {
            "name": "dimensions",
            "description": "Zero or more dimensions that will be reduced by the model. Fails with a `DimensionNotAvailable` exception if one of the specified dimensions does not exist.",
            "schema": {
                "type": "array",
                "items": {
                    "type": "string"
                }
            }
        }
    ],
    "returns": {
        "description": "A data cube with the predicted class probabilities. It removes the specified dimensions and adds a new dimension for the class probabilities. The dimension has the name `classes` and is of type `other`. Each label in the dimension represents a class, and the values are the probabilities for each class.",
        "schema": {
            "type": "object",
            "subtype": "datacube",
            "dimensions": [
                {
                    "type": "other"
                }
            ]
        }
    }
}